CHANGES.txt
LICENSE.txt
bootstrap.py
buildout.cfg
setup.py
src/lovely/__init__.py
src/lovely.tal.egg-info/PKG-INFO
src/lovely.tal.egg-info/SOURCES.txt
src/lovely.tal.egg-info/dependency_links.txt
src/lovely.tal.egg-info/namespace_packages.txt
src/lovely.tal.egg-info/not-zip-safe
src/lovely.tal.egg-info/requires.txt
src/lovely.tal.egg-info/top_level.txt
src/lovely/tal/LICENSE.txt
src/lovely/tal/README.txt
src/lovely/tal/SETUP.cfg
src/lovely/tal/__init__.py
src/lovely/tal/configure.zcml
src/lovely/tal/lovely.tal-configure.zcml
src/lovely/tal/sample.pt
src/lovely/tal/tests.py
src/lovely/tal/textformatter.py