Metadata-Version: 1.0
Name: lovely.tal
Version: 0.6.0
Summary: the lovely tal enables new tal expressions
Home-page: http://launchpad.net/lovely.tal
Author: Lovely Systems GmbH
Author-email: office@lovelysystems.com
License: ZPL 2.1
Keywords: tal zope zope3
Platform: UNKNOWN
Classifier: Development Status :: 4 - Beta
Classifier: Intended Audience :: Developers
Classifier: License :: OSI Approved :: Zope Public License
Classifier: Topic :: Software Development :: Libraries :: Python Modules
